aliyunsdkltl/__init__.py
aliyunsdkltl/endpoint.py
aliyunsdkltl/request/__init__.py
aliyunsdkltl/request/v20190510/ApplyDataModelConfigInfoRequest.py
aliyunsdkltl/request/v20190510/AttachDataRequest.py
aliyunsdkltl/request/v20190510/AttachDataWithSignatureRequest.py
aliyunsdkltl/request/v20190510/AuthorizeDeviceGroupRequest.py
aliyunsdkltl/request/v20190510/AuthorizeDeviceRequest.py
aliyunsdkltl/request/v20190510/BatchUploadMPCoSPhaseDigestInfoByDeviceRequest.py
aliyunsdkltl/request/v20190510/BatchUploadMPCoSPhaseDigestInfoRequest.py
aliyunsdkltl/request/v20190510/BatchUploadMPCoSPhaseTextInfoByDeviceRequest.py
aliyunsdkltl/request/v20190510/BatchUploadMPCoSPhaseTextInfoRequest.py
aliyunsdkltl/request/v20190510/CreateMPCoSPhaseGroupRequest.py
aliyunsdkltl/request/v20190510/CreateMPCoSPhaseRequest.py
aliyunsdkltl/request/v20190510/CreateMemberRequest.py
aliyunsdkltl/request/v20190510/DescribeCapacityInfoRequest.py
aliyunsdkltl/request/v20190510/DescribeMPCoSAuthorizedInfoRequest.py
aliyunsdkltl/request/v20190510/DescribeMPCoSPhaseInfoRequest.py
aliyunsdkltl/request/v20190510/DescribeMPCoSResourceInfoRequest.py
aliyunsdkltl/request/v20190510/DescribeMemberCapacityInfoRequest.py
aliyunsdkltl/request/v20190510/DescribeResourceInfoRequest.py
aliyunsdkltl/request/v20190510/GetBlockChainInfoRequest.py
aliyunsdkltl/request/v20190510/GetDataModelConfigInfoRequest.py
aliyunsdkltl/request/v20190510/GetDataRequest.py
aliyunsdkltl/request/v20190510/GetHistoryDataCountRequest.py
aliyunsdkltl/request/v20190510/GetHistoryDataListRequest.py
aliyunsdkltl/request/v20190510/ListDependentDataModelsRequest.py
aliyunsdkltl/request/v20190510/ListDeviceGroupRequest.py
aliyunsdkltl/request/v20190510/ListDeviceRequest.py
aliyunsdkltl/request/v20190510/ListMPCoSPhaseGroupRequest.py
aliyunsdkltl/request/v20190510/ListMPCoSPhaseHistoryRequest.py
aliyunsdkltl/request/v20190510/ListMPCoSPhaseRequest.py
aliyunsdkltl/request/v20190510/ListMemberRequest.py
aliyun_python_sdk_ltl-1.0.0.dist-info/LICENSE
aliyun_python_sdk_ltl-1.0.0.dist-info/METADATA
aliyun_python_sdk_ltl-1.0.0.dist-info/WHEEL
aliyun_python_sdk_ltl-1.0.0.dist-info/top_level.txt
aliyun_python_sdk_ltl-1.0.0.dist-info/RECORD
